setup.py
armada_heal/__init__.py
armada_heal/armada-heal
armada_heal/armada_heal.py
armada_heal.egg-info/PKG-INFO
armada_heal.egg-info/SOURCES.txt
armada_heal.egg-info/dependency_links.txt
armada_heal.egg-info/requires.txt
armada_heal.egg-info/top_level.txt