Metadata-Version: 1.0
Name: armada-heal
Version: 0.0.3
Summary: Script for healing overloaded armada ship.
Home-page: http://dev.git.gd/armada/armada-heal
Author: Cerebro
Author-email: cerebro@ganymede.eu
License: UNKNOWN
Platform: UNKNOWN
